<?xml version="1.0" encoding="UTF-8" standalone="yes"?>
<atms>
    <atm>
        <bills>
            <bill>
                <key>12</key>
                <value>10</value>
            </bill>
        </bills>
        <id>ATM-1</id>
        <status>true</status>
    </atm>
    <atm>
        <bills>
            <bill>
                <key>17</key>
                <value>12</value>
            </bill>
            <bill>
                <key>21</key>
                <value>17</value>
            </bill>
            <bill>
                <key>14</key>
                <value>16</value>
            </bill>
        </bills>
        <id>ATM-2</id>
        <status>true</status>
    </atm>
    <atm>
        <bills>
            <bill>
                <key>16</key>
                <value>22</value>
            </bill>
            <bill>
                <key>22</key>
                <value>14</value>
            </bill>
            <bill>
                <key>30</key>
                <value>24</value>
            </bill>
        </bills>
        <id>ATM-3</id>
        <status>true</status>
    </atm>
    <atm>
        <bills>
            <bill>
                <key>18</key>
                <value>28</value>
            </bill>
            <bill>
                <key>39</key>
                <value>31</value>
            </bill>
            <bill>
                <key>27</key>
                <value>16</value>
            </bill>
        </bills>
        <id>ATM-4</id>
        <status>true</status>
    </atm>
    <atm>
        <bills>
            <bill>
                <key>32</key>
                <value>18</value>
            </bill>
            <bill>
                <key>48</key>
                <value>38</value>
            </bill>
            <bill>
                <key>20</key>
                <value>34</value>
            </bill>
        </bills>
        <id>ATM-5</id>
        <status>true</status>
    </atm>
    <blocked>false</blocked>
</atms>
